autotrainer/api/__init__.py
autotrainer/api/api_event_kind.py
autotrainer/api/api_options.py
autotrainer/api/rpc_service.py
autotrainer/api/util.py
autotrainer/api/command/__init__.py
autotrainer/api/command/api_command.py
autotrainer/api/command/configuration_response.py
autotrainer/api/command/status_response.py
autotrainer/api/telemtry/__init__.py
autotrainer/api/telemtry/open_telemetry_service.py
autotrainer/api/zeromq/__init__.py
autotrainer/api/zeromq/zeromq_api_service.py
auto_trainer_api-0.9.8.dist-info/METADATA
auto_trainer_api-0.9.8.dist-info/WHEEL
auto_trainer_api-0.9.8.dist-info/RECORD
