Metadata-Version: 2.4
Name: auto-trainer-api
Version: 0.9.8
Summary: API for interfacing with the core acquisition process via platform and language agnostic message queues.
License: AGPL-3.0-only
Classifier: Operating System :: OS Independent
Classifier: Programming Language :: Python :: 3
Requires-Python: >=3.8
Requires-Dist: pyhumps==3.8.0
Requires-Dist: pyzmq==26.4
Provides-Extra: telemetry
Requires-Dist: opentelemetry-api; extra == 'telemetry'
Requires-Dist: opentelemetry-sdk; extra == 'telemetry'
Provides-Extra: test
Requires-Dist: pytest==8.2.0; extra == 'test'
